{
  "login_id": "pgopi",
  "id": 398,
  "project_name": "organization_proj",
  "pipeline_name": "organization_pipeline",
  "project_id": 60,
  "pipeline_id": 149,
  "task_name": "bulk_aws_s3_to_mysql",
  "task_description": "bulk_aws_s3_to_mysql",
  "task_type": "Bulk Ingestion",
  "task_sequence": "0",
  "updated_dttm": "2024-03-14T12:00:41.000Z",
  "source": "Files",
  "target": "DB",
  "is_active": "Y",
  "created_by": "jjones",
  "updated_by": "jjones",
  "chunk_size": 10000,
  "source_type": "Files",
  "target_type": "DB",
  "job_execution": "Pandas",
  "restartability": "normal",
  "task": {
    "details": [
      {
        "subtask": "1",
        "source": {
          "header": "Y",
          "connection_name": "aws_s3",
          "encoding": "utf-8",
          "delimiter": ",",
          "file_path": "demo/landing/",
          "operation": "copy",
          "quote_char": "\"",
          "task_group": "0",
          "escape_char": "\\",
          "object_name": "lnd_dim_customer_profile_2024.csv",
          "object_type": "csv",
          "transfer_mode": "binary",
          "files_filter_name": "*_2024.csv",
          "subfolder_included": "no",
          "skip_footer":None,
          "skip_header":None
        },
        "target": {
          "object_name": "lnd_dim_customer_profile",
          "connection_name": "mysql",
          "primary_key": "",
          "schema_name": "test",
          "audit_fields": "YES",
          "database_name": "test",
          "action_on_table": "CREATE IF NOT"
        }
      },
      {
        "subtask": "2",
        "source": {
          "header": "Y",
          "connection_name": "aws_s3",
          "encoding": "utf-8",
          "delimiter": ",",
          "file_path": "demo/landing/",
          "operation": "copy",
          "quote_char": "\"",
          "task_group": "1",
          "escape_char": "\\",
          "object_name": "lnd_employee_details_2024.csv",
          "object_type": "csv",
          "transfer_mode": "binary",
          "files_filter_name": "*_2024.csv",
          "subfolder_included": "no",
          "skip_footer": None,
          "skip_header":None
        },
        "target": {
          "object_name": "lnd_employee_details",
          "connection_name": "mysql",
          "primary_key": "",
          "schema_name": "test",
          "audit_fields": "YES",
          "database_name": "test",
          "action_on_table": "CREATE IF NOT"
        }
      }
    ]
  }
}
