{
  "login_id": "pgopi",
  "id": 411,
  "project_name": "organization_proj",
  "pipeline_name": "organization_pipeline",
  "project_id": 60,
  "pipeline_id": 149,
  "task_name": "decrypt_json_to_xml",
  "task_description": "decrypt_json_to_xml",
  "task_type": "Ingestion",
  "task_sequence": "0",
  "updated_dttm": "2024-04-03T14:21:18.000Z",
  "source": "Local Server",
  "target": "Local Server",
  "is_active": "Y",
  "created_by": "jjones",
  "updated_by": "jjones",
  "task": {
    "source": {
      "source_type": "json_read",
      "header": "Y",
      "encoding": "utf-8",
      "delimiter": ",",
      "file_name": "cancel.json.gpg",
      "file_path": "/home/rperuman/src_files/encryption/",
      "file_type": "json",
      "chunk_size": 10000,
      "encryption": "yes",
      "quote_char": null,
      "compression": "",
      "escape_char": null,
      "skip_footer": null,
      "skip_header": null,
      "alias_columns": null,
      "parameter_type": "Local Server",
      "select_columns": null,
      "connection_name": "localserver",
      "private_key_path": "Hercules@1927!"
    },
    "target": {
      "target_type": "xlsx_write",
      "header": "Y",
      "encoding": "utf-8",
      "delimiter": ",",
      "file_name": "cancel_2.json",
      "file_path": "/home/rperuman/src_files/encryption/",
      "file_type": "xlsx",
      "encryption": "no",
      "compression": "",
      "audit_columns": "inactive",
      "parameter_type": "Local Server",
      "connection_name": "localserver",
      "public_key_path": "",
      "target_max_record_count": null
    },
    "data_quality_execution": {
      "pre_check_enable": "N",
      "post_check_enable": "N"
    }
  }
}